odoo9_addon_intrastat_base-9.0.1.0.0-py2.7-nspkg.pth
odoo9_addon_intrastat_base-9.0.1.0.0.dist-info/DESCRIPTION.rst
odoo9_addon_intrastat_base-9.0.1.0.0.dist-info/METADATA
odoo9_addon_intrastat_base-9.0.1.0.0.dist-info/RECORD
odoo9_addon_intrastat_base-9.0.1.0.0.dist-info/WHEEL
odoo9_addon_intrastat_base-9.0.1.0.0.dist-info/metadata.json
odoo9_addon_intrastat_base-9.0.1.0.0.dist-info/namespace_packages.txt
odoo9_addon_intrastat_base-9.0.1.0.0.dist-info/top_level.txt
odoo_addons/intrastat_base/README.rst
odoo_addons/intrastat_base/__init__.py
odoo_addons/intrastat_base/__openerp__.py
odoo_addons/intrastat_base/data/country_data.xml
odoo_addons/intrastat_base/demo/intrastat_demo.xml
odoo_addons/intrastat_base/i18n/intrastat_base.pot
odoo_addons/intrastat_base/models/__init__.py
odoo_addons/intrastat_base/models/account_tax.py
odoo_addons/intrastat_base/models/intrastat_common.py
odoo_addons/intrastat_base/models/product_template.py
odoo_addons/intrastat_base/models/res_company.py
odoo_addons/intrastat_base/models/res_country.py
odoo_addons/intrastat_base/tests/__init__.py
odoo_addons/intrastat_base/tests/intrastat_base_tests.py
odoo_addons/intrastat_base/views/account_tax.xml
odoo_addons/intrastat_base/views/intrastat.xml
odoo_addons/intrastat_base/views/product_template.xml
odoo_addons/intrastat_base/views/res_company.xml
odoo_addons/intrastat_base/views/res_country.xml
odoo_addons/intrastat_base/views/res_partner.xml
